bcdb/__init__.py
bcdb/py.typed
bcdb-0.4.0.dist-info/LICENSE
bcdb-0.4.0.dist-info/METADATA
bcdb-0.4.0.dist-info/WHEEL
bcdb-0.4.0.dist-info/top_level.txt
bcdb-0.4.0.dist-info/RECORD
