Metadata-Version: 2.1
Name: bcdb
Version: 0.4.0
Summary: Black Cat DataBase is a simple database.
Home-page: https://github.com/koviubi56/bcdb
Author: Koviubi56
Author-email: koviubi56@duck.com
License: GPL
Keywords: db,database
Platform: unix
Platform: linux
Platform: osx
Platform: cygwin
Platform: win32
Classifier: Development Status :: 3 - Alpha
Classifier: License :: OSI Approved :: GNU General Public License v3 or later (GPLv3+)
Classifier: Natural Language :: English
Classifier: Operating System :: OS Independent
Classifier: Programming Language :: Python :: 3
Classifier: Programming Language :: Python :: 3 :: Only
Classifier: Programming Language :: Python :: 3.11
Classifier: Programming Language :: Python :: 3.12
Classifier: Programming Language :: Python :: Implementation :: CPython
Classifier: Topic :: Database
Classifier: Typing :: Typed
Requires-Python: >=3.11
License-File: LICENSE
Requires-Dist: typing-extensions (>=4.0.0)
